README.md
setup.py
shift2/__init__.py
shift2/__main__.py
shift2/layers.py
shift2/shcrypt.py
shift_tool.egg-info/PKG-INFO
shift_tool.egg-info/SOURCES.txt
shift_tool.egg-info/dependency_links.txt
shift_tool.egg-info/entry_points.txt
shift_tool.egg-info/top_level.txt