Metadata-Version: 2.1
Name: shift-tool
Version: 3.0.2
Summary: Not an encryption tool
Home-page: https://github.com/Ewpratten/shift
Author: Evan Pratten
Author-email: ewpratten@gmail.com
License: UNKNOWN
Platform: UNKNOWN
Classifier: Programming Language :: Python :: 3
Classifier: Operating System :: OS Independent
Classifier: Development Status :: 5 - Production/Stable
